[
  {
    "type": "info",
    "seed": 3143242112,
    "countVertex": 5,
    "density": 0,
    "size": 7
  },
  {
    "type": "startPoint",
    "x": 2.0,
    "y": 2.0
  },
  {
    "type": "endPoint",
    "x": 98.0,
    "y": 98.0
  },
  {
    "type": "polygon",
    "points": [
      {
        "type": "point",
        "x": 13.040863037109375,
        "y": 31.490379333496094
      },
      {
        "type": "point",
        "x": 12.439901351928711,
        "y": 23.798072814941406
      },
      {
        "type": "point",
        "x": 85.5168228149414,
        "y": 21.274032592773438
      },
      {
        "type": "point",
        "x": 86.35816955566406,
        "y": 29.447105407714844
      }
    ]
  },
  {
    "type": "polygon",
    "points": [
      {
        "type": "point",
        "x": 78.78604888916016,
        "y": 92.4278793334961
      },
      {
        "type": "point",
        "x": 72.29566192626953,
        "y": 70.91345977783203
      },
      {
        "type": "point",
        "x": 96.57450866699219,
        "y": 83.29326629638672
      }
    ]
  },
  {
    "type": "polygon",
    "points": [
      {
        "type": "point",
        "x": 62.9206657409668,
        "y": 43.749996185302734
      },
      {
        "type": "point",
        "x": 57.27163314819336,
        "y": 71.27403259277344
      },
      {
        "type": "point",
        "x": 51.141822814941406,
        "y": 74.39903259277344
      },
      {
        "type": "point",
        "x": 57.9927864074707,
        "y": 46.39422607421875
      }
    ]
  },
  {
    "type": "polygon",
    "points": [
      {
        "type": "point",
        "x": 19.771631240844727,
        "y": 64.3028793334961
      },
      {
        "type": "point",
        "x": 44.77163314819336,
        "y": 53.24518966674805
      },
      {
        "type": "point",
        "x": 57.27163314819336,
        "y": 71.15383911132813
      },
      {
        "type": "point",
        "x": 53.18509292602539,
        "y": 91.34614562988281
      }
    ]
  }
]